transformer_thermal_model/__init__.py
transformer_thermal_model/aging/__init__.py
transformer_thermal_model/aging/aging.py
transformer_thermal_model/components/__init__.py
transformer_thermal_model/components/bushing_config.py
transformer_thermal_model/components/deprecation_enum_meta.py
transformer_thermal_model/components/transformer_side.py
transformer_thermal_model/components/vector_config.py
transformer_thermal_model/cooler/__init__.py
transformer_thermal_model/cooler/cooler_type.py
transformer_thermal_model/hot_spot_calibration/__init__.py
transformer_thermal_model/hot_spot_calibration/calibrate_hotspot_factor.py
transformer_thermal_model/model/__init__.py
transformer_thermal_model/model/thermal_model.py
transformer_thermal_model/schemas/__init__.py
transformer_thermal_model/schemas/specifications/__init__.py
transformer_thermal_model/schemas/specifications/transformer.py
transformer_thermal_model/schemas/specifications/transformer_component.py
transformer_thermal_model/schemas/thermal_model/__init__.py
transformer_thermal_model/schemas/thermal_model/initial_state.py
transformer_thermal_model/schemas/thermal_model/input_profile.py
transformer_thermal_model/schemas/thermal_model/onaf_switch.py
transformer_thermal_model/schemas/thermal_model/output_profile.py
transformer_thermal_model/toolbox/__init__.py
transformer_thermal_model/toolbox/temp_sim_profile_tools.py
transformer_thermal_model/transformer/__init__.py
transformer_thermal_model/transformer/base.py
transformer_thermal_model/transformer/cooling_switch_controller.py
transformer_thermal_model/transformer/distribution.py
transformer_thermal_model/transformer/enums/__init__.py
transformer_thermal_model/transformer/enums/paper_insulation_type.py
transformer_thermal_model/transformer/enums/transformer_type.py
transformer_thermal_model/transformer/power.py
transformer_thermal_model/transformer/threewinding.py
transformer_thermal_model-0.5.0.dist-info/METADATA
transformer_thermal_model-0.5.0.dist-info/WHEEL
transformer_thermal_model-0.5.0.dist-info/licenses/LICENSE
transformer_thermal_model-0.5.0.dist-info/licenses/LICENSES/CC-BY-4.0.txt
transformer_thermal_model-0.5.0.dist-info/licenses/LICENSES/MPL-2.0.txt
transformer_thermal_model-0.5.0.dist-info/RECORD
