Metadata-Version: 2.4
Name: transformer-thermal-model
Version: 0.5.0
Summary: Thermal model for transformers
License-File: LICENSE
License-File: LICENSES/CC-BY-4.0.txt
License-File: LICENSES/MPL-2.0.txt
Author: Contributors to the Transformer Thermal Model project
Requires-Python: >=3.11, <4.0
Classifier: Natural Language :: English
Classifier: Operating System :: OS Independent
Classifier: Programming Language :: Python :: 3
Requires-Dist: numpy (>=2.2.5,<3)
Requires-Dist: pandas (>=2.0,<3.0)
Requires-Dist: pydantic (>=2.11.1,<3)
